pygame_xml_gui/__init__.py
pygame_xml_gui/src/classes/errorHandler.py
pygame_xml_gui/src/classes/guiMaker.py
pygame_xml_gui/src/classes/sizeInserter.py
pygame_xml_gui/src/classes/sourceInserter.py
pygame_xml_gui/src/classes/sourceReader.py
pygame_xml_gui/src/classes/styleImporter.py
pygame_xml_gui/src/classes/styleInserter.py
pygame_xml_gui/src/classes/validator.py
pygame_xml_gui/src/classes/widget.py
pygame_xml_gui/src/classes/widgetPrinter.py
pygame_xml_gui/src/classes/xmlAttributeValidator.py
pygame_xml_gui/src/classes/xmlHandler.py
pygame_xml_gui/src/classes/xmlHelper.py
pygame_xml_gui/src/files/paths.py
pygame_xml_gui/src/files/pyStyle/dark.json
pygame_xml_gui/src/files/pyStyle/default.json
pygame_xml_gui/src/files/schema/xml_schema.py
pygame_xml_gui/src/files/schema/xml_schema.xsd
pygame_xml_gui/src/UserInterface.py
pygame_xml_gui/src/UserInterfaceConstructor.py
pygame_xml_gui/test/test_dp/test_dp.py
pygame_xml_gui/test/test_dp/test_dp.xml
pygame_xml_gui/test/test_entry/test_entry.py
pygame_xml_gui/test/test_entry/test_entry.xml
pygame_xml_gui/test/test_points/test_points.json
pygame_xml_gui/test/test_points/test_points.py
pygame_xml_gui/test/test_points/test_points.xml
pygame_xml_gui/test/test_set_from_string/test_set_from_string.py
pygame_xml_gui/test/test_UserInterfaceConstructor/test_uic.json
pygame_xml_gui/test/test_UserInterfaceConstructor/test_uic.py
pygame_xml_gui/test/test_UserInterfaceConstructor/test_uic.xml
pygame_xml_gui/test/test_UserInterfaceConstructor/test_uic_source.py
pygame_xml_gui-0.2.8.dist-info/LICENSE.txt
pygame_xml_gui-0.2.8.dist-info/METADATA
pygame_xml_gui-0.2.8.dist-info/WHEEL
pygame_xml_gui-0.2.8.dist-info/RECORD
